Metadata-Version: 1.1
Name: pytestorz
Version: 0.0.1
Summary: This is a log library, you can output json and care fields easy.
Home-page: https://github.com/CzaOrz/loggus
Author: CzaOrz
Author-email: 972542644@qq.com
License: UNKNOWN
Platform: UNKNOWN
Classifier: Programming Language :: Python :: 3.6
Classifier: Programming Language :: Python :: 3.7
Classifier: Programming Language :: Python :: 3.8
